__init__.py
clima.py
excel.py
festivos.py
main.py
prediccion.py
pronostico_panaderia-1.0.2.dist-info/METADATA
pronostico_panaderia-1.0.2.dist-info/WHEEL
pronostico_panaderia-1.0.2.dist-info/top_level.txt
pronostico_panaderia-1.0.2.dist-info/RECORD
